MANIFEST.in
README.rst
bootstrap.py
buildout.cfg
experiments.sh
setup.py
estimate/__init__.py
estimate.gender.egg-info/PKG-INFO
estimate.gender.egg-info/SOURCES.txt
estimate.gender.egg-info/dependency_links.txt
estimate.gender.egg-info/entry_points.txt
estimate.gender.egg-info/namespace_packages.txt
estimate.gender.egg-info/requires.txt
estimate.gender.egg-info/top_level.txt
estimate/gender/__init__.py
estimate/gender/estimateGender.py
estimate/gender/rank_all.py
estimate/gender/test_all.py