Metadata-Version: 1.0
Name: estimate.gender
Version: 0.3
Summary: Gender estimation on several databases
Home-page: UNKNOWN
Author: Nesli Erdogmus
Author-email: nesli.erdogmus@idiap.ch
License: GPLv3
Platform: UNKNOWN
